{"__symbolic":"module","version":4,"metadata":{"CovalentNavLinksModule":{"__symbolic":"class","decorators":[{"__symbolic":"call","expression":{"__symbolic":"reference","module":"@angular/core","name":"NgModule","line":14,"character":1},"arguments":[{"declarations":[{"__symbolic":"reference","name":"ɵa"}],"exports":[{"__symbolic":"reference","name":"ɵa"}],"imports":[{"__symbolic":"reference","module":"@angular/common","name":"CommonModule","line":18,"character":4},{"__symbolic":"reference","module":"@covalent/core/common","name":"CovalentCommonModule","line":19,"character":4},{"__symbolic":"reference","module":"@covalent/core/expansion-panel","name":"CovalentExpansionPanelModule","line":20,"character":4},{"__symbolic":"reference","module":"@angular/material/list","name":"MatListModule","line":21,"character":4},{"__symbolic":"reference","module":"@angular/material/icon","name":"MatIconModule","line":22,"character":4},{"__symbolic":"reference","module":"@angular/material/divider","name":"MatDividerModule","line":23,"character":4},{"__symbolic":"reference","module":"@angular/router","name":"RouterModule","line":24,"character":4}]}]}],"members":{}},"ɵa":{"__symbolic":"class","decorators":[{"__symbolic":"call","expression":{"__symbolic":"reference","module":"@angular/core","name":"Component","line":18,"character":1},"arguments":[{"selector":"td-nav-links","changeDetection":{"__symbolic":"select","expression":{"__symbolic":"reference","module":"@angular/core","name":"ChangeDetectionStrategy","line":22,"character":19},"member":"OnPush"},"template":"<mat-nav-list dense *ngIf=\"links && links.length > 0\">\n  <ng-template ngFor [ngForOf]=\"links\" let-linkGroup let-indexGroup=\"index\">\n    <td-expansion-panel\n      *ngIf=\"linkGroup.name && linkGroup.links.length\"\n      class=\"td-nav-group\"\n      [sublabel]=\"linkGroup.name\"\n      [expand]=\"true\"\n    >\n      <mat-divider></mat-divider>\n      <ng-template [ngTemplateOutlet]=\"links\"></ng-template>\n    </td-expansion-panel>\n    <ng-template *ngIf=\"!linkGroup.name && linkGroup.links.length\" [ngTemplateOutlet]=\"links\"></ng-template>\n    <ng-template #links>\n      <ng-template ngFor [ngForOf]=\"linkGroup.links\" let-link let-indexLink=\"index\">\n        <a\n          mat-list-item\n          *ngIf=\"link.linkTo.href && (link.show === undefined || link.show)\"\n          [href]=\"link.linkTo.href\"\n          [target]=\"link.openInNewTab ? '_blank' : '_self'\"\n          id=\"{{ id }}-{{ indexGroup }}-{{ indexLink }}\"\n          class=\"td-nav-link\"\n          (click)=\"linkClicked(link)\"\n        >\n          <mat-icon matListIcon [fontSet]=\"link.fontSet\">{{ link.icon }}</mat-icon>\n          <span matLine>{{ link.label }}</span>\n        </a>\n\n        <a\n          mat-list-item\n          *ngIf=\"link.linkTo.routerLink && (link.show === undefined || link.show)\"\n          [routerLink]=\"link.linkTo.routerLink\"\n          [target]=\"link.openInNewTab ? '_blank' : null\"\n          id=\"{{ id }}-{{ indexGroup }}-{{ indexLink }}\"\n          class=\"td-nav-link\"\n          (click)=\"linkClicked(link)\"\n        >\n          <mat-icon matListIcon [fontSet]=\"link.fontSet\">{{ link.icon }}</mat-icon>\n          <span matLine>{{ link.label }}</span>\n        </a>\n      </ng-template>\n    </ng-template>\n  </ng-template>\n</mat-nav-list>\n","styles":[":host{display:block}:host .mat-nav-list.mat-list-base{padding-top:2px}:host .mat-icon{margin-right:0}"]}]}],"members":{"id":[{"__symbolic":"property","decorators":[{"__symbolic":"call","expression":{"__symbolic":"reference","module":"@angular/core","name":"Input","line":27,"character":3}}]}],"links":[{"__symbolic":"property","decorators":[{"__symbolic":"call","expression":{"__symbolic":"reference","module":"@angular/core","name":"Input","line":28,"character":3}}]}],"afterClick":[{"__symbolic":"property","decorators":[{"__symbolic":"call","expression":{"__symbolic":"reference","module":"@angular/core","name":"Output","line":29,"character":3}}]}],"linkClicked":[{"__symbolic":"method"}]}}},"origins":{"CovalentNavLinksModule":"./nav-links.module","ɵa":"./nav-links.component"},"importAs":"@covalent/core/nav-links"}